README.txt
setup.py
bioinfo_tools/__init__.py
bioinfo_tools.egg-info/PKG-INFO
bioinfo_tools.egg-info/SOURCES.txt
bioinfo_tools.egg-info/dependency_links.txt
bioinfo_tools.egg-info/requires.txt
bioinfo_tools.egg-info/top_level.txt
bioinfo_tools/genomic_features/__init__.py
bioinfo_tools/genomic_features/chromosome.py
bioinfo_tools/genomic_features/gene.py
bioinfo_tools/genomic_features/genome.py
bioinfo_tools/genomic_features/transcript.py
bioinfo_tools/parsers/__init__.py
bioinfo_tools/parsers/fasta.py
bioinfo_tools/parsers/gff.py
bioinfo_tools/parsers/obo.py
bioinfo_tools/utils/__init__.py
bioinfo_tools/utils/log.py
bioinfo_tools/utils/ncbi.py
bioinfo_tools/utils/sge.py