Metadata-Version: 1.1
Name: bioinfo-tools
Version: 0.3.1
Summary: Python library that parses GFF, Fasta files into python classes
Home-page: https://github.com/sebriois/bioinfo_tools
Author: Sebastien Briois, Guillaume Tiberi
Author-email: sebriois@gmail.com
License: BSD
Keywords: bioinformatics
Platform: UNKNOWN
Classifier: Environment :: Web Environment
Classifier: Intended Audience :: Developers
Classifier: License :: OSI Approved :: BSD License
Classifier: Operating System :: OS Independent
Classifier: Programming Language :: Python
Classifier: Topic :: Scientific/Engineering :: Bio-Informatics
